tomography_tutorial/__init__.py
tomography_tutorial/ancillary.py
tomography_tutorial/functions.py
tomography_tutorial/plotting.py
tomography_tutorial/tutorial.ipynb
tomography_tutorial-1.0.1.dist-info/LICENSE
tomography_tutorial-1.0.1.dist-info/METADATA
tomography_tutorial-1.0.1.dist-info/WHEEL
tomography_tutorial-1.0.1.dist-info/top_level.txt
tomography_tutorial-1.0.1.dist-info/RECORD
