Metadata-Version: 2.1
Name: tomography-tutorial
Version: 1.0.1
Summary: A tutorial package for Synthetic Aperture Radar Tomography
Home-page: https://github.com/EO-College/tomography_tutorial
Author: John Truckenbrodt
Author-email: john.truckenbrodt@uni-jena.de
License: GPL-3
Classifier: Programming Language :: Python
Requires-Python: >3.0.0
License-File: LICENSE
Requires-Dist: numpy
Requires-Dist: jupyter
Requires-Dist: matplotlib
Requires-Dist: scipy
